{
  "버전": "v9.2",
  "티어": "메테오라이트+",
  "통계": {
    "2025-10-30 16:28": [
      {
        "실험체": "방망이 가넷",
        "RP 획득": 37.0,
        "표본수": 1,
        "승률": 0.0,
        "TOP 3": 1.0,
        "평균 순위": 3.0,
        "픽률": 0.0192
      },
      {
        "실험체": "권총 니아",
        "RP 획득": 18.5,
        "표본수": 2,
        "승률": 0.0,
        "TOP 3": 0.5,
        "평균 순위": 3.0,
        "픽률": 0.0385
      },
      {
        "실험체": "글러브 니키",
        "RP 획득": -26.0,
        "표본수": 1,
        "승률": 0.0,
        "TOP 3": 0.0,
        "평균 순위": 5.0,
        "픽률": 0.0192
      },
      {
        "실험체": "단검 다니엘",
        "RP 획득": -48.0,
        "표본수": 1,
        "승률": 0.0,
        "TOP 3": 0.0,
        "평균 순위": 7.0,
        "픽률": 0.0192
      },
      {
        "실험체": "돌격 소총 아이솔",
        "RP 획득": 32.0,
        "표본수": 1,
        "승률": 0.0,
        "TOP 3": 1.0,
        "평균 순위": 3.0,
        "픽률": 0.0192
      },
      {
        "실험체": "돌격 소총 헤이즈",
        "RP 획득": 107.0,
        "표본수": 1,
        "승률": 1.0,
        "TOP 3": 1.0,
        "평균 순위": 1.0,
        "픽률": 0.0192
      },
      {
        "실험체": "채찍 라우라",
        "RP 획득": 44.0,
        "표본수": 1,
        "승률": 0.0,
        "TOP 3": 1.0,
        "평균 순위": 2.0,
        "픽률": 0.0192
      },
      {
        "실험체": "채찍 레녹스",
        "RP 획득": -38.0,
        "표본수": 1,
        "승률": 0.0,
        "TOP 3": 0.0,
        "평균 순위": 6.0,
        "픽률": 0.0192
      },
      {
        "실험체": "권총 레니",
        "RP 획득": -2.0,
        "표본수": 1,
        "승률": 0.0,
        "TOP 3": 0.0,
        "평균 순위": 4.0,
        "픽률": 0.0192
      },
      {
        "실험체": "글러브 레온",
        "RP 획득": -53.0,
        "표본수": 1,
        "승률": 0.0,
        "TOP 3": 0.0,
        "평균 순위": 7.0,
        "픽률": 0.0192
      },
      {
        "실험체": "방망이 루크",
        "RP 획득": -34.0,
        "표본수": 2,
        "승률": 0.0,
        "TOP 3": 0.0,
        "평균 순위": 5.5,
        "픽률": 0.0385
      },
      {
        "실험체": "기타 르노어",
        "RP 획득": 44.0,
        "표본수": 1,
        "승률": 0.0,
        "TOP 3": 1.0,
        "평균 순위": 2.0,
        "픽률": 0.0192
      },
      {
        "실험체": "글러브 리 다이린",
        "RP 획득": 95.0,
        "표본수": 1,
        "승률": 0.0,
        "TOP 3": 1.0,
        "평균 순위": 2.0,
        "픽률": 0.0192
      },
      {
        "실험체": "카메라 마르티나",
        "RP 획득": -28.0,
        "표본수": 1,
        "승률": 0.0,
        "TOP 3": 0.0,
        "평균 순위": 5.0,
        "픽률": 0.0192
      },
      {
        "실험체": "저격총 버니스",
        "RP 획득": -9.0,
        "표본수": 1,
        "승률": 0.0,
        "TOP 3": 1.0,
        "평균 순위": 3.0,
        "픽률": 0.0192
      },
      {
        "실험체": "아르카나 비앙카",
        "RP 획득": -41.0,
        "표본수": 1,
        "승률": 0.0,
        "TOP 3": 0.0,
        "평균 순위": 7.0,
        "픽률": 0.0192
      },
      {
        "실험체": "단검 쇼이치",
        "RP 획득": -30.0,
        "표본수": 1,
        "승률": 0.0,
        "TOP 3": 0.0,
        "평균 순위": 6.0,
        "픽률": 0.0192
      },
      {
        "실험체": "방망이 수아",
        "RP 획득": 56.0,
        "표본수": 2,
        "승률": 0.5,
        "TOP 3": 0.5,
        "평균 순위": 3.5,
        "픽률": 0.0385
      },
      {
        "실험체": "암기 시셀라",
        "RP 획득": 107.0,
        "표본수": 1,
        "승률": 1.0,
        "TOP 3": 1.0,
        "평균 순위": 1.0,
        "픽률": 0.0192
      },
      {
        "실험체": "권총 실비아",
        "RP 획득": -37.0,
        "표본수": 1,
        "승률": 0.0,
        "TOP 3": 0.0,
        "평균 순위": 6.0,
        "픽률": 0.0192
      },
      {
        "실험체": "레이피어 아델라",
        "RP 획득": 160.0,
        "표본수": 1,
        "승률": 1.0,
        "TOP 3": 1.0,
        "평균 순위": 1.0,
        "픽률": 0.0192
      },
      {
        "실험체": "아르카나 아디나",
        "RP 획득": -35.0,
        "표본수": 1,
        "승률": 0.0,
        "TOP 3": 0.0,
        "평균 순위": 5.0,
        "픽률": 0.0192
      },
      {
        "실험체": "아르카나 아르다",
        "RP 획득": 95.0,
        "표본수": 1,
        "승률": 0.0,
        "TOP 3": 1.0,
        "평균 순위": 2.0,
        "픽률": 0.0192
      },
      {
        "실험체": "권총 아이솔",
        "RP 획득": -30.0,
        "표본수": 1,
        "승률": 0.0,
        "TOP 3": 0.0,
        "평균 순위": 6.0,
        "픽률": 0.0192
      },
      {
        "실험체": "톤파 아이작",
        "RP 획득": -15.5,
        "표본수": 2,
        "승률": 0.0,
        "TOP 3": 0.0,
        "평균 순위": 4.5,
        "픽률": 0.0385
      },
      {
        "실험체": "톤파 알렉스",
        "RP 획득": 107.0,
        "표본수": 1,
        "승률": 1.0,
        "TOP 3": 1.0,
        "평균 순위": 1.0,
        "픽률": 0.0192
      },
      {
        "실험체": "글러브 알론소",
        "RP 획득": -9.0,
        "표본수": 1,
        "승률": 0.0,
        "TOP 3": 1.0,
        "평균 순위": 3.0,
        "픽률": 0.0192
      },
      {
        "실험체": "톤파 얀",
        "RP 획득": 31.3,
        "표본수": 3,
        "승률": 0.3333,
        "TOP 3": 0.3333,
        "평균 순위": 4.0,
        "픽률": 0.0577
      },
      {
        "실험체": "암기 엠마",
        "RP 획득": -2.0,
        "표본수": 1,
        "승률": 0.0,
        "TOP 3": 0.0,
        "평균 순위": 4.0,
        "픽률": 0.0192
      },
      {
        "실험체": "투척 윌리엄",
        "RP 획득": 2.3,
        "표본수": 3,
        "승률": 0.0,
        "TOP 3": 0.3333,
        "평균 순위": 4.3,
        "픽률": 0.0577
      },
      {
        "실험체": "양손검 재키",
        "RP 획득": 20.0,
        "표본수": 3,
        "승률": 0.0,
        "TOP 3": 0.6667,
        "평균 순위": 3.0,
        "픽률": 0.0577
      },
      {
        "실험체": "암기 츠바메",
        "RP 획득": 70.0,
        "표본수": 2,
        "승률": 0.5,
        "TOP 3": 0.5,
        "평균 순위": 2.5,
        "픽률": 0.0385
      },
      {
        "실험체": "저격총 카티야",
        "RP 획득": -53.0,
        "표본수": 1,
        "승률": 0.0,
        "TOP 3": 0.0,
        "평균 순위": 7.0,
        "픽률": 0.0192
      },
      {
        "실험체": "도끼 케네스",
        "RP 획득": -50.0,
        "표본수": 1,
        "승률": 0.0,
        "TOP 3": 0.0,
        "평균 순위": 5.0,
        "픽률": 0.0192
      },
      {
        "실험체": "저격총 테오도르",
        "RP 획득": -9.0,
        "표본수": 1,
        "승률": 0.0,
        "TOP 3": 1.0,
        "평균 순위": 3.0,
        "픽률": 0.0192
      },
      {
        "실험체": "레이피어 피오라",
        "RP 획득": 37.0,
        "표본수": 1,
        "승률": 0.0,
        "TOP 3": 1.0,
        "평균 순위": 3.0,
        "픽률": 0.0192
      },
      {
        "실험체": "쌍절곤 피올로",
        "RP 획득": 99.5,
        "표본수": 2,
        "승률": 0.5,
        "TOP 3": 1.0,
        "평균 순위": 2.0,
        "픽률": 0.0385
      },
      {
        "실험체": "암기 혜진",
        "RP 획득": -40.0,
        "표본수": 2,
        "승률": 0.0,
        "TOP 3": 0.0,
        "평균 순위": 5.5,
        "픽률": 0.0385
      },
      {
        "실험체": "활 혜진",
        "RP 획득": -38.0,
        "표본수": 1,
        "승률": 0.0,
        "TOP 3": 0.0,
        "평균 순위": 6.0,
        "픽률": 0.0192
      }
    ]
  }
}